sentembeddings/__init__.py
sentembeddings/resources/.DS_Store
sentembeddings/resources/model/1_Pooling/config.json
sentembeddings/resources/model/README.md
sentembeddings/resources/model/config.json
sentembeddings/resources/model/config_sentence_transformers.json
sentembeddings/resources/model/modules.json
sentembeddings/resources/model/pytorch_model.bin
sentembeddings/resources/model/sentence_bert_config.json
sentembeddings/resources/model/special_tokens_map.json
sentembeddings/resources/model/tokenizer.json
sentembeddings/resources/model/tokenizer_config.json
sentembeddings/resources/model/vocab.txt
sentembeddings/sentembeddings.py
sentembeddings-0.0.1.dist-info/METADATA
sentembeddings-0.0.1.dist-info/WHEEL
sentembeddings-0.0.1.dist-info/RECORD
