Metadata-Version: 2.1
Name: sentembeddings
Version: 0.0.1
Summary: lightweight sentence embeddings for python
Author: wayfaring-stranger
Author-email: zw6p226m@duck.com
Requires-Python: >=3.9,<4.0
Classifier: Programming Language :: Python :: 3
Classifier: Programming Language :: Python :: 3.9
Classifier: Programming Language :: Python :: 3.10
Classifier: Programming Language :: Python :: 3.11
Requires-Dist: torch (>=1.9.0,<2.0.0)
Requires-Dist: transformers (>=4.12.0,<5.0.0)
